plantbgc/README.md
plantbgc/__init__.py
plantbgc/__version__.py
plantbgc/data.py
plantbgc/features.py
plantbgc/main.py
plantbgc/try.py
plantbgc/util.py
plantbgc/Predict/__init__.py
plantbgc/Predict/annotator.py
plantbgc/Predict/classifier.py
plantbgc/Predict/data
plantbgc/Predict/detector.py
plantbgc/Predict/merge.py
plantbgc/Predict/pfam.py
plantbgc/Predict/protein.py
plantbgc/Predict/step.py
plantbgc/command/GO_Proxy.py
plantbgc/command/KEGG_Proxy.py
plantbgc/command/Predict.py
plantbgc/command/__init__.py
plantbgc/command/base.py
plantbgc/command/download.py
plantbgc/command/info.py
plantbgc/command/merge.py
plantbgc/command/prepare.py
plantbgc/command/train.py
plantbgc/models/__init__.py
plantbgc/models/hmm.py
plantbgc/models/random_forest.py
plantbgc/models/rnn.py
plantbgc/models/transformer.json
plantbgc/models/transformer.py
plantbgc/models/wrapper.py
plantbgc/output/GO_Proxy.py
plantbgc/output/KEGG_Proxy.py
plantbgc/output/__init__.py
plantbgc/output/antismash_json.py
plantbgc/output/bgc_genbank.py
plantbgc/output/cluster_tsv.py
plantbgc/output/genbank.py
plantbgc/output/merge.py
plantbgc/output/pfam_tsv.py
plantbgc/output/readme.py
plantbgc/output/writer.py
plantbgc/output/data/go_prim.txt
plantbgc/output/data/go_sec.txt
plantbgc/output/data/ko2class_cache.json
plantbgc/output/data/ko_prim.txt
plantbgc/output/data/ko_sec.txt
plantbgc/output/data/pfam2go.txt
plantbgc/output/evaluation/__init__.py
plantbgc/output/evaluation/bgc_region_plot.py
plantbgc/output/evaluation/data
plantbgc/output/evaluation/pfam_score_plot.py
plantbgc/output/evaluation/pr_plot.py
plantbgc/output/evaluation/roc_plot.py
plantbgc-0.1.0.dist-info/LICENSE
plantbgc-0.1.0.dist-info/LICENSES_THIRD_PARTY
plantbgc-0.1.0.dist-info/METADATA
plantbgc-0.1.0.dist-info/WHEEL
plantbgc-0.1.0.dist-info/entry_points.txt
plantbgc-0.1.0.dist-info/top_level.txt
plantbgc-0.1.0.dist-info/RECORD
