Metadata-Version: 2.1
Name: plantbgc
Version: 0.1.0
Summary: PlantBGC: Transformer-based biosynthetic gene cluster candidate detection for plant genomes
Home-page: https://github.com/Yuhanzhao-233/PlantBGC
Author: PlantBGC Authors
Author-email: Yuhan Zhao <yzhao66@ncsu.edu>
License: MIT
Keywords: bioinformatics,BGC,transformer,plants
Classifier: Programming Language :: Python :: 3
Classifier: License :: OSI Approved :: MIT License
Classifier: Operating System :: OS Independent
Requires-Python: >=3.6,<3.8
License-File: LICENSE
License-File: LICENSES_THIRD_PARTY
Requires-Dist: biopython >=1.78
Requires-Dist: numpy ==1.16.1
Requires-Dist: pandas ==0.24.1
Requires-Dist: scikit-learn ==0.21.3
Requires-Dist: scipy ==1.2.0
Requires-Dist: matplotlib ==2.2.3
Requires-Dist: keras ==2.2.4
Requires-Dist: tensorflow ==1.15.4
Requires-Dist: appdirs >=1.4.3
Requires-Dist: protobuf <4
Provides-Extra: hmm
Requires-Dist: hmmlearn <0.2.7,>=0.2.1 ; extra == 'hmm'
